[
  {
    "test_id": "20250619_164655",
    "event_type": "theoretical",
    "device_count": 90,
    "device_ids": [
      "REALME2029313300B",
      "REALME2030416359A",
      "RAZER2035386847H",
      "ASUS2034678685A",
      "HUAWEI2035133182F",
      "ASUS2027140695H",
      "HONOR2033423244D",
      "ASUS2027868282E",
      "ACER2035220193F",
      "DELL2026021787B",
      "OPPO2025436682C",
      "REALME2033134947B",
      "XIAOMI2028928515F",
      "HONOR2035484920G",
      "RAZER2027954526J",
      "IQOO2027009934F",
      "APPLE2035755584D",
      "XIAOMI2029678435J",
      "NOKIA2031351451G",
      "HONOR2031264141D",
      "APPLE2028921226A",
      "APPLE2032047591G",
      "RAZER2034225944I",
      "NOKIA2025408942A",
      "REALME2027046395E",
      "OPPO2029762223A",
      "REALME2027977800C",
      "HUAWEI2028778712I",
      "VIVO2034860136D",
      "VIVO2031099345B",
      "DELL2026261180F",
      "REALME2034802380D",
      "OPPO2034758512C",
      "HONOR2025847434I",
      "OPPO2029729887E",
      "HUAWEI2027886691E",
      "IQOO2035245006G",
      "HUAWEI2029207300H",
      "IQOO2027353695F",
      "HONOR2025241413G",
      "HONOR2026359157D",
      "ACER2030578291G",
      "HONOR2026377754D",
      "APPLE2028745307I",
      "OPPO2032700071H",
      "ASUS2027716608C",
      "HUAWEI2032744018A",
      "VIVO2026058788E",
      "OPPO2033756432J",
      "DELL2026634035F",
      "HUAWEI2026032921A",
      "DELL2035262157A",
      "HONOR2027513560H",
      "HUAWEI2025094235E",
      "APPLE2034551727E",
      "REALME2030352044F",
      "REALME2034821409B",
      "HUAWEI2033777596A",
      "OPPO2025545358B",
      "HONOR2031888437B",
      "HUAWEI2025929944H",
      "NOKIA2035198641A",
      "XIAOMI2026178819H",
      "ASUS2034386588B",
      "RAZER2027867620C",
      "ASUS2033821460B",
      "ACER2032742870B",
      "RAZER2034040864A",
      "APPLE2029068332A",
      "OPPO2029951691J",
      "NOKIA2027382476D",
      "APPLE2033224714D",
      "OPPO2026780158B",
      "ACER2033863750D",
      "VIVO2026820073C",
      "IQOO2034028668H",
      "RAZER2030480393I",
      "OPPO2025416938G",
      "VIVO2031120372D",
      "HONOR2029326619D",
      "VIVO2028244891B",
      "ASUS2028668942D",
      "NOKIA2026779396I",
      "HUAWEI2032743004C",
      "XIAOMI2035681275E",
      "IQOO2030618599B",
      "REALME2029035563F",
      "REALME2035435875E",
      "VIVO2028573131A",
      "OPPO2030159419E"
    ],
    "timestamp": "2025-06-19T16:47:21.748423"
  },
  {
    "test_id": "20250619_164655",
    "event_type": "actual",
    "device_count": 0,
    "device_ids": [],
    "timestamp": "2025-06-19T16:47:21.870745"
  },
  {
    "test_id": "20250619_195645",
    "event_type": "theoretical",
    "device_count": 24,
    "device_ids": [
      "HUAWEI2033777596A",
      "OPPO2029762223A",
      "OPPO2032700071H",
      "NOKIA2031351451G",
      "VIVO2031099345B",
      "ASUS2027140695H",
      "XIAOMI2028928515F",
      "APPLE2028921226A",
      "VIVO2031120372D",
      "XIAOMI2026178819H",
      "IQOO2030618599B",
      "NOKIA2035198641A",
      "HONOR2025847434I",
      "HUAWEI2025094235E",
      "HUAWEI2032743004C",
      "ASUS2034386588B",
      "APPLE2029068332A",
      "OPPO2025436682C",
      "RAZER2034225944I",
      "HUAWEI2026032921A",
      "OPPO2034758512C",
      "OPPO2029951691J",
      "HUAWEI2032744018A",
      "OPPO2025545358B"
    ],
    "timestamp": "2025-06-19T19:57:28.374918"
  },
  {
    "test_id": "20250619_200015",
    "event_type": "theoretical",
    "device_count": 24,
    "device_ids": [
      "VIVO2031120372D",
      "HUAWEI2033777596A",
      "OPPO2029762223A",
      "XIAOMI2026178819H",
      "OPPO2025545358B",
      "HUAWEI2026032921A",
      "IQOO2030618599B",
      "NOKIA2031351451G",
      "HONOR2025847434I",
      "HUAWEI2025094235E",
      "ASUS2027140695H",
      "OPPO2025436682C",
      "XIAOMI2028928515F",
      "APPLE2029068332A",
      "OPPO2029951691J",
      "RAZER2034225944I",
      "HUAWEI2032743004C",
      "ASUS2034386588B",
      "OPPO2034758512C",
      "NOKIA2035198641A",
      "VIVO2031099345B",
      "OPPO2032700071H",
      "APPLE2028921226A",
      "HUAWEI2032744018A"
    ],
    "timestamp": "2025-06-19T20:00:43.667796"
  },
  {
    "test_id": "20250619_200015",
    "event_type": "actual",
    "device_count": 0,
    "device_ids": [],
    "timestamp": "2025-06-19T20:00:44.372887"
  },
  {
    "test_id": "20250619_200149",
    "event_type": "theoretical",
    "device_count": 24,
    "device_ids": [
      "IQOO2030618599B",
      "VIVO2031120372D",
      "XIAOMI2026178819H",
      "OPPO2025545358B",
      "HUAWEI2026032921A",
      "HUAWEI2032744018A",
      "ASUS2034386588B",
      "OPPO2034758512C",
      "RAZER2034225944I",
      "OPPO2029951691J",
      "OPPO2029762223A",
      "HUAWEI2025094235E",
      "HUAWEI2033777596A",
      "VIVO2031099345B",
      "APPLE2029068332A",
      "ASUS2027140695H",
      "APPLE2028921226A",
      "OPPO2025436682C",
      "HUAWEI2032743004C",
      "NOKIA2035198641A",
      "OPPO2032700071H",
      "HONOR2025847434I",
      "NOKIA2031351451G",
      "XIAOMI2028928515F"
    ],
    "timestamp": "2025-06-19T20:02:23.881741"
  },
  {
    "test_id": "20250619_200149",
    "event_type": "actual",
    "device_count": 0,
    "device_ids": [],
    "timestamp": "2025-06-19T20:02:28.202742"
  },
  {
    "test_id": "20250619_203406",
    "event_type": "theoretical",
    "device_count": 24,
    "device_ids": [
      "APPLE2029068332A",
      "HUAWEI2033777596A",
      "VIVO2031099345B",
      "OPPO2025545358B",
      "HUAWEI2025094235E",
      "OPPO2029951691J",
      "HONOR2025847434I",
      "HUAWEI2032744018A",
      "ASUS2027140695H",
      "XIAOMI2026178819H",
      "HUAWEI2026032921A",
      "OPPO2032700071H",
      "HUAWEI2032743004C",
      "OPPO2025436682C",
      "RAZER2034225944I",
      "OPPO2029762223A",
      "APPLE2028921226A",
      "NOKIA2035198641A",
      "XIAOMI2028928515F",
      "IQOO2030618599B",
      "VIVO2031120372D",
      "ASUS2034386588B",
      "OPPO2034758512C",
      "NOKIA2031351451G"
    ],
    "timestamp": "2025-06-19T20:34:36.410178"
  },
  {
    "test_id": "20250619_203406",
    "event_type": "actual",
    "device_count": 0,
    "device_ids": [],
    "timestamp": "2025-06-19T20:34:37.949691"
  },
  {
    "test_id": "20250619_204247",
    "event_type": "theoretical",
    "device_count": 24,
    "device_ids": [
      "OPPO2032700071H",
      "OPPO2029951691J",
      "IQOO2030618599B",
      "OPPO2034758512C",
      "RAZER2034225944I",
      "HUAWEI2025094235E",
      "NOKIA2035198641A",
      "HUAWEI2032743004C",
      "OPPO2025436682C",
      "VIVO2031120372D",
      "ASUS2027140695H",
      "HUAWEI2032744018A",
      "OPPO2029762223A",
      "APPLE2029068332A",
      "OPPO2025545358B",
      "XIAOMI2028928515F",
      "XIAOMI2026178819H",
      "ASUS2034386588B",
      "APPLE2028921226A",
      "HUAWEI2033777596A",
      "NOKIA2031351451G",
      "VIVO2031099345B",
      "HONOR2025847434I",
      "HUAWEI2026032921A"
    ],
    "timestamp": "2025-06-19T20:43:17.397785"
  },
  {
    "test_id": "20250619_204247",
    "event_type": "actual",
    "device_count": 0,
    "device_ids": [],
    "timestamp": "2025-06-19T20:43:18.536055"
  },
  {
    "test_id": "20250619_204339",
    "event_type": "theoretical",
    "device_count": 24,
    "device_ids": [
      "HUAWEI2026032921A",
      "APPLE2029068332A",
      "NOKIA2031351451G",
      "XIAOMI2026178819H",
      "NOKIA2035198641A",
      "XIAOMI2028928515F",
      "VIVO2031099345B",
      "HUAWEI2032743004C",
      "ASUS2034386588B",
      "OPPO2034758512C",
      "OPPO2025545358B",
      "HONOR2025847434I",
      "HUAWEI2033777596A",
      "OPPO2025436682C",
      "ASUS2027140695H",
      "OPPO2032700071H",
      "HUAWEI2032744018A",
      "OPPO2029951691J",
      "VIVO2031120372D",
      "RAZER2034225944I",
      "APPLE2028921226A",
      "IQOO2030618599B",
      "OPPO2029762223A",
      "HUAWEI2025094235E"
    ],
    "timestamp": "2025-06-19T20:44:09.050411"
  },
  {
    "test_id": "20250619_204339",
    "event_type": "actual",
    "device_count": 0,
    "device_ids": [],
    "timestamp": "2025-06-19T20:44:10.031899"
  },
  {
    "test_id": "20250619_204958",
    "event_type": "theoretical",
    "device_count": 24,
    "device_ids": [
      "ASUS2034386588B",
      "HUAWEI2032744018A",
      "HONOR2025847434I",
      "OPPO2025545358B",
      "OPPO2032700071H",
      "OPPO2025436682C",
      "IQOO2030618599B",
      "HUAWEI2033777596A",
      "APPLE2029068332A",
      "NOKIA2031351451G",
      "ASUS2027140695H",
      "OPPO2029951691J",
      "OPPO2029762223A",
      "OPPO2034758512C",
      "HUAWEI2026032921A",
      "RAZER2034225944I",
      "HUAWEI2025094235E",
      "HUAWEI2032743004C",
      "VIVO2031099345B",
      "VIVO2031120372D",
      "XIAOMI2026178819H",
      "APPLE2028921226A",
      "XIAOMI2028928515F",
      "NOKIA2035198641A"
    ],
    "timestamp": "2025-06-19T20:50:28.982960"
  },
  {
    "test_id": "20250619_204958",
    "event_type": "actual",
    "device_count": 0,
    "device_ids": [],
    "timestamp": "2025-06-19T20:50:30.103848"
  },
  {
    "test_id": "20250619_205050",
    "event_type": "theoretical",
    "device_count": 24,
    "device_ids": [
      "OPPO2029951691J",
      "HUAWEI2032743004C",
      "OPPO2029762223A",
      "OPPO2025545358B",
      "HUAWEI2025094235E",
      "RAZER2034225944I",
      "APPLE2029068332A",
      "IQOO2030618599B",
      "VIVO2031120372D",
      "ASUS2027140695H",
      "VIVO2031099345B",
      "HUAWEI2032744018A",
      "OPPO2025436682C",
      "OPPO2032700071H",
      "NOKIA2031351451G",
      "XIAOMI2028928515F",
      "ASUS2034386588B",
      "HUAWEI2026032921A",
      "XIAOMI2026178819H",
      "OPPO2034758512C",
      "HUAWEI2033777596A",
      "APPLE2028921226A",
      "HONOR2025847434I",
      "NOKIA2035198641A"
    ],
    "timestamp": "2025-06-19T20:51:20.163813"
  },
  {
    "test_id": "20250619_205050",
    "event_type": "actual",
    "device_count": 0,
    "device_ids": [],
    "timestamp": "2025-06-19T20:51:21.207031"
  },
  {
    "test_id": "20250619_205609",
    "event_type": "theoretical",
    "device_count": 24,
    "device_ids": [
      "OPPO2032700071H",
      "HUAWEI2033777596A",
      "APPLE2028921226A",
      "HUAWEI2026032921A",
      "NOKIA2031351451G",
      "OPPO2029951691J",
      "OPPO2025545358B",
      "NOKIA2035198641A",
      "ASUS2034386588B",
      "XIAOMI2026178819H",
      "OPPO2034758512C",
      "ASUS2027140695H",
      "VIVO2031099345B",
      "HUAWEI2032743004C",
      "RAZER2034225944I",
      "OPPO2029762223A",
      "VIVO2031120372D",
      "HUAWEI2025094235E",
      "XIAOMI2028928515F",
      "OPPO2025436682C",
      "HONOR2025847434I",
      "APPLE2029068332A",
      "HUAWEI2032744018A",
      "IQOO2030618599B"
    ],
    "timestamp": "2025-06-19T20:56:38.081593"
  },
  {
    "test_id": "20250619_205609",
    "event_type": "actual",
    "device_count": 0,
    "device_ids": [],
    "timestamp": "2025-06-19T20:56:39.099100"
  },
  {
    "test_id": "20250619_205635",
    "event_type": "theoretical",
    "device_count": 24,
    "device_ids": [
      "OPPO2029951691J",
      "ASUS2027140695H",
      "VIVO2031120372D",
      "VIVO2031099345B",
      "HUAWEI2032744018A",
      "HUAWEI2026032921A",
      "OPPO2025436682C",
      "RAZER2034225944I",
      "HONOR2025847434I",
      "APPLE2029068332A",
      "IQOO2030618599B",
      "OPPO2025545358B",
      "OPPO2034758512C",
      "OPPO2029762223A",
      "XIAOMI2028928515F",
      "HUAWEI2032743004C",
      "ASUS2034386588B",
      "OPPO2032700071H",
      "HUAWEI2033777596A",
      "NOKIA2035198641A",
      "HUAWEI2025094235E",
      "APPLE2028921226A",
      "NOKIA2031351451G",
      "XIAOMI2026178819H"
    ],
    "timestamp": "2025-06-19T20:57:01.703866"
  },
  {
    "test_id": "20250619_205635",
    "event_type": "actual",
    "device_count": 0,
    "device_ids": [],
    "timestamp": "2025-06-19T20:57:02.445014"
  },
  {
    "test_id": "20250620_175715",
    "event_type": "theoretical",
    "device_count": 22,
    "device_ids": [
      "IQOO2030618599B",
      "OPPO2029951691J",
      "XIAOMI2028928515F",
      "VIVO2031120372D",
      "ASUS2034386588B",
      "OPPO2032700071H",
      "OPPO2029762223A",
      "HUAWEI2025094235E",
      "XIAOMI2026178819H",
      "RAZER2034225944I",
      "HUAWEI2032744018A",
      "VIVO2031099345B",
      "HUAWEI2032743004C",
      "APPLE2028921226A",
      "NOKIA2035198641A",
      "HUAWEI2026032921A",
      "NOKIA2031351451G",
      "OPPO2025545358B",
      "HONOR2025847434I",
      "OPPO2025436682C",
      "ASUS2027140695H",
      "HUAWEI2033777596A"
    ],
    "timestamp": "2025-06-20T17:57:40.315829"
  },
  {
    "test_id": "20250620_175715",
    "event_type": "actual",
    "device_count": 0,
    "device_ids": [],
    "timestamp": "2025-06-20T17:57:40.758083"
  },
  {
    "test_id": "20250620_180433",
    "event_type": "theoretical",
    "device_count": 22,
    "device_ids": [
      "NOKIA2031351451G",
      "HUAWEI2032744018A",
      "HUAWEI2033777596A",
      "XIAOMI2026178819H",
      "OPPO2032700071H",
      "IQOO2030618599B",
      "APPLE2028921226A",
      "VIVO2031099345B",
      "OPPO2029951691J",
      "XIAOMI2028928515F",
      "NOKIA2035198641A",
      "ASUS2027140695H",
      "VIVO2031120372D",
      "ASUS2034386588B",
      "HUAWEI2026032921A",
      "OPPO2029762223A",
      "HONOR2025847434I",
      "OPPO2025545358B",
      "RAZER2034225944I",
      "HUAWEI2025094235E",
      "OPPO2025436682C",
      "HUAWEI2032743004C"
    ],
    "timestamp": "2025-06-20T18:05:00.145353"
  },
  {
    "test_id": "20250620_180433",
    "event_type": "actual",
    "device_count": 0,
    "device_ids": [],
    "timestamp": "2025-06-20T18:05:00.663403"
  },
  {
    "test_id": "20250620_180626",
    "event_type": "theoretical",
    "device_count": 22,
    "device_ids": [
      "OPPO2029762223A",
      "IQOO2030618599B",
      "HONOR2025847434I",
      "OPPO2032700071H",
      "OPPO2025545358B",
      "OPPO2029951691J",
      "HUAWEI2026032921A",
      "APPLE2028921226A",
      "HUAWEI2025094235E",
      "HUAWEI2033777596A",
      "RAZER2034225944I",
      "VIVO2031120372D",
      "HUAWEI2032743004C",
      "VIVO2031099345B",
      "XIAOMI2028928515F",
      "ASUS2027140695H",
      "ASUS2034386588B",
      "NOKIA2031351451G",
      "OPPO2025436682C",
      "NOKIA2035198641A",
      "HUAWEI2032744018A",
      "XIAOMI2026178819H"
    ],
    "timestamp": "2025-06-20T18:06:57.872215"
  },
  {
    "test_id": "20250620_180626",
    "event_type": "actual",
    "device_count": 0,
    "device_ids": [],
    "timestamp": "2025-06-20T18:06:58.220928"
  }
]